vus/__init__.py
vus/basic_metrics.py
vus/metrics.py
vus/affiliation/__init__.py
vus/affiliation/_affiliation_zone.py
vus/affiliation/_integral_interval.py
vus/affiliation/_single_ground_truth_event.py
vus/affiliation/generics.py
vus/affiliation/metrics.py
vus/analysis/__init__.py
vus/analysis/robustness_eval.py
vus/analysis/score_computation.py
vus/models/AE.py
vus/models/__init__.py
vus/models/cnn.py
vus/models/damp.py
vus/models/detectorA.py
vus/models/detectorB.py
vus/models/distance.py
vus/models/feature.py
vus/models/hbos.py
vus/models/iforest.py
vus/models/lof.py
vus/models/lstm.py
vus/models/matrix_profile.py
vus/models/ocsvm.py
vus/models/pca.py
vus/models/poly.py
vus/models/sand.py
vus/models/sklearn_base.py
vus/utils/__init__.py
vus/utils/metrics.py
vus/utils/slidingWindows.py
vus/utils/stat_models.py
vus/utils/utility.py
vus-0.0.6.dist-info/METADATA
vus-0.0.6.dist-info/WHEEL
vus-0.0.6.dist-info/top_level.txt
vus-0.0.6.dist-info/zip-safe
vus-0.0.6.dist-info/RECORD
